{"@context":{"@protected":true,"EncryptedPortfolio":"rhp:EncryptedPortfolio","SelfAssertion":"rhp:SelfAssertion","assertedAt":{"@id":"rhp:assertedAt","@type":"http://www.w3.org/2001/XMLSchema#dateTime"},"claims":"rhp:claims","hiri":"https://hiri-protocol.org/vocab#","holderAuthority":"rhp:holderAuthority","passport":"https://hiri-protocol.org/passport#","rhp":"https://hiri-protocol.org/resources/preview/rhp-2026-07/vocab#","schema":{"@id":"rhp:schema","@type":"@id"},"schemaHash":"rhp:schemaHash","schemaVersion":"rhp:schemaVersion","subjectHolderAuthority":"rhp:subjectHolderAuthority"}}