{"$id":"https://hiri-protocol.org/resources/preview/rhp-2026-07/schemas/presentation-package/v1","$schema":"https://json-schema.org/draft/2020-12/schema","additionalProperties":false,"properties":{"artifacts":{"items":{"additionalProperties":false,"properties":{"canonicalization":{"const":"JCS"},"contentHash":{"pattern":"^sha256:[0-9a-f]{64}$","type":"string"},"kind":{"enum":["hiriManifest","jsonContent","jsonSchema"]},"manifestHash":{"pattern":"^sha256:[0-9a-f]{64}$","type":"string"},"schema":{"minLength":1,"type":"string"},"schemaHash":{"pattern":"^sha256:[0-9a-f]{64}$","type":"string"},"value":{}},"required":["kind","value"],"type":"object"},"maxItems":128,"type":"array"},"presentation":{},"protocol":{"const":"hiri-passport/2.0"},"type":{"const":"PassportPresentationPackage"}},"required":["protocol","type","presentation","artifacts"],"title":"RHP Passport Presentation Package transport container","type":"object"}